[
	{
		"key": "Healthy",
		"color": "#00cc00",
		"values": [
			{
				"label": "Onsite",
				"value": 34
			},
			{
				"label": "Offsite",
				"value": 7
			}
		]
	},
	{
		"key": "Neutral",
		"color": "#ff9900",
		"values": [
			{
				"label": "Onsite",
				"value": 8
			},
			{
				"label": "Offsite",
				"value": 4
			}
		]
	},
	{
		"key": "Harmful",
		"color": "#ff0000",
		"values": [
			{
				"label": "Onsite",
				"value": -0
			},
			{
				"label": "Offsite",
				"value": -12
			}
		]
	}
]
