{
	"offsite": {
		"number_of_images_missing_alt": [
			{
				"html_id": "http://www.upvcfrenchdoors.org.uk/hardwood-double-glazing/",
				"feature_value": "1",
				"cluster_win_mean": " 11.2",
				"delta": " 10.2"
			},
			{
				"html_id": "http://www.upvcpatiodoors.org.uk/hardwood-double-glazing/",
				"feature_value": "1",
				"cluster_win_mean": "16.36",
				"delta": "15.36"
			},
			{
				"html_id": "http://newyork-press-release.com/94/Brits-Enjoy-Best-Choice-Home-Improvement-Companies-Thanks-Doubleglazinglocal-Local-Search-34587775-print.php",
				"feature_value": "2",
				"cluster_win_mean": "16.36",
				"delta": "14.36"
			}
		],
		"number_of_scripts": [
			{
				"html_id": "http://www.upvcfrenchdoors.org.uk/hardwood-double-glazing/",
				"feature_value": " 0",
				"cluster_win_mean": "17.88",
				"delta": "17.88"
			},
			{
				"html_id": "http://www.upvcpatiodoors.org.uk/hardwood-double-glazing/",
				"feature_value": "17",
				"cluster_win_mean": " 12.8",
				"delta": " -4.2"
			},
			{
				"html_id": "http://newyork-press-release.com/94/Brits-Enjoy-Best-Choice-Home-Improvement-Companies-Thanks-Doubleglazinglocal-Local-Search-34587775-print.php",
				"feature_value": "17",
				"cluster_win_mean": " 12.8",
				"delta": " -4.2"
			}
		],
		"number_of_images_in_body": {
			"html_id": "http://www.upvcfrenchdoors.org.uk/hardwood-double-glazing/",
			"feature_value": "1",
			"cluster_win_mean": "11.27",
			"delta": "10.27"
		},
		"html5_detected": [
			{
				"html_id": "http://www.upvcfrenchdoors.org.uk/hardwood-double-glazing/",
				"feature_value": "0",
				"cluster_win_mean": "1",
				"delta": "1"
			},
			{
				"html_id": "http://www.upvcpatiodoors.org.uk/hardwood-double-glazing/",
				"feature_value": "0",
				"cluster_win_mean": "1",
				"delta": "1"
			},
			{
				"html_id": "http://newyork-press-release.com/94/Brits-Enjoy-Best-Choice-Home-Improvement-Companies-Thanks-Doubleglazinglocal-Local-Search-34587775-print.php",
				"feature_value": "0",
				"cluster_win_mean": "1",
				"delta": "1"
			}
		],
		"maximum_length_of_h1": [
			{
				"html_id": "http://www.upvcpatiodoors.org.uk/hardwood-double-glazing/",
				"feature_value": " 0",
				"cluster_win_mean": "70.6",
				"delta": "70.6"
			},
			{
				"html_id": "http://newyork-press-release.com/94/Brits-Enjoy-Best-Choice-Home-Improvement-Companies-Thanks-Doubleglazinglocal-Local-Search-34587775-print.php",
				"feature_value": "25",
				"cluster_win_mean": "70.6",
				"delta": "45.6"
			}
		],
		"average_length_of_h1": {
			"html_id": "http://newyork-press-release.com/94/Brits-Enjoy-Best-Choice-Home-Improvement-Companies-Thanks-Doubleglazinglocal-Local-Search-34587775-print.php",
			"feature_value": "25",
			"cluster_win_mean": "45.52",
			"delta": "20.52"
		},
		"number_of_embedded_styles": [
			{
				"html_id": "http://www.upvcpatiodoors.org.uk/hardwood-double-glazing/",
				"feature_value": "2",
				"cluster_win_mean": "2.9",
				"delta": "0.9"
			},
			{
				"html_id": "http://newyork-press-release.com/94/Brits-Enjoy-Best-Choice-Home-Improvement-Companies-Thanks-Doubleglazinglocal-Local-Search-34587775-print.php",
				"feature_value": "2",
				"cluster_win_mean": "2.9",
				"delta": "0.9"
			}
		],
		"maximum_length_of_h2": [
			{
				"html_id": "http://www.upvcfrenchdoors.org.uk/hardwood-double-glazing/",
				"feature_value": " 0",
				"cluster_win_mean": "52.07",
				"delta": "52.07"
			},
			{
				"html_id": "http://www.upvcpatiodoors.org.uk/hardwood-double-glazing/",
				"feature_value": " 0",
				"cluster_win_mean": "71.79",
				"delta": "71.79"
			},
			{
				"html_id": "http://newyork-press-release.com/94/Brits-Enjoy-Best-Choice-Home-Improvement-Companies-Thanks-Doubleglazinglocal-Local-Search-34587775-print.php",
				"feature_value": "10",
				"cluster_win_mean": "71.79",
				"delta": "61.79"
			}
		],
		"average_length_of_h2": [
			{
				"html_id": "http://www.upvcfrenchdoors.org.uk/hardwood-double-glazing/",
				"feature_value": " 0",
				"cluster_win_mean": "51.77",
				"delta": "51.77"
			},
			{
				"html_id": "http://www.upvcpatiodoors.org.uk/hardwood-double-glazing/",
				"feature_value": " 0",
				"cluster_win_mean": "71.22",
				"delta": "71.22"
			},
			{
				"html_id": "http://newyork-press-release.com/94/Brits-Enjoy-Best-Choice-Home-Improvement-Companies-Thanks-Doubleglazinglocal-Local-Search-34587775-print.php",
				"feature_value": "10",
				"cluster_win_mean": "71.22",
				"delta": "61.22"
			}
		],
		"number_of_dhtml_scripts": [
			{
				"html_id": "http://www.upvcfrenchdoors.org.uk/hardwood-double-glazing/",
				"feature_value": "0",
				"cluster_win_mean": "1.16",
				"delta": "1.16"
			},
			{
				"html_id": "http://www.upvcpatiodoors.org.uk/hardwood-double-glazing/",
				"feature_value": "0",
				"cluster_win_mean": "1.31",
				"delta": "1.31"
			},
			{
				"html_id": "http://newyork-press-release.com/94/Brits-Enjoy-Best-Choice-Home-Improvement-Companies-Thanks-Doubleglazinglocal-Local-Search-34587775-print.php",
				"feature_value": "0",
				"cluster_win_mean": "1.31",
				"delta": "1.31"
			}
		]
	}
}
